defoldsdk/__init__.py
defoldsdk/ddf/__init__.py
defoldsdk/ddf/ddf_extensions_pb2.py
defoldsdk/ddf/ddf_math_pb2.py
defoldsdk/engine/__init__.py
defoldsdk/engine/engine_ddf_pb2.py
defoldsdk/gameobject/__init__.py
defoldsdk/gameobject/gameobject_ddf_pb2.py
defoldsdk/gameobject/lua_ddf_pb2.py
defoldsdk/gameobject/properties_ddf_pb2.py
defoldsdk/gamesys/__init__.py
defoldsdk/gamesys/atlas_ddf_pb2.py
defoldsdk/gamesys/buffer_ddf_pb2.py
defoldsdk/gamesys/camera_ddf_pb2.py
defoldsdk/gamesys/gamesys_ddf_pb2.py
defoldsdk/gamesys/gui_ddf_pb2.py
defoldsdk/gamesys/label_ddf_pb2.py
defoldsdk/gamesys/mesh_ddf_pb2.py
defoldsdk/gamesys/model_ddf_pb2.py
defoldsdk/gamesys/physics_ddf_pb2.py
defoldsdk/gamesys/sound_ddf_pb2.py
defoldsdk/gamesys/sprite_ddf_pb2.py
defoldsdk/gamesys/texture_set_ddf_pb2.py
defoldsdk/gamesys/tile_ddf_pb2.py
defoldsdk/graphics/__init__.py
defoldsdk/graphics/graphics_ddf_pb2.py
defoldsdk/render/__init__.py
defoldsdk/render/font_ddf_pb2.py
defoldsdk/render/material_ddf_pb2.py
defoldsdk/render/render_ddf_pb2.py
defoldsdk/resource/__init__.py
defoldsdk/resource/liveupdate_ddf_pb2.py
defoldsdk/resource/resource_ddf_pb2.py
defoldsdk/script/__init__.py
defoldsdk/script/ddf_script_pb2.py
defoldsdk/script/lua_source_ddf_pb2.py
defoldsdk/script/sys_ddf_pb2.py
defoldsdk-1.3.7.dist-info/LICENSE
defoldsdk-1.3.7.dist-info/METADATA
defoldsdk-1.3.7.dist-info/WHEEL
defoldsdk-1.3.7.dist-info/top_level.txt
defoldsdk-1.3.7.dist-info/RECORD
