Metadata-Version: 2.1
Name: defoldsdk
Version: 1.3.7
Summary: Defold protobuff compiled to python package
Home-page: https://github.com/MhadhbiXissam/defoldsdk.git
Author: issam Mhadhbi
Author-email: mhadhbixissam@gmail.com
License: UNKNOWN
Project-URL: Documentation, https://github.com/MhadhbiXissam/defoldsdk/tree/main/doc
Project-URL: Source, https://github.com/MhadhbiXissam/defoldsdk.git
Platform: UNKNOWN
Classifier: Programming Language :: Python :: 3
Classifier: License :: OSI Approved :: MIT License
Requires-Python: >=3.8
License-File: LICENSE
Requires-Dist: protobuf
Requires-Dist: requests
